fibonacci/__init__.py
fibonacci/fibonacci.py
py_fibonacci-0.5.2.dist-info/LICENSE
py_fibonacci-0.5.2.dist-info/METADATA
py_fibonacci-0.5.2.dist-info/WHEEL
py_fibonacci-0.5.2.dist-info/top_level.txt
py_fibonacci-0.5.2.dist-info/RECORD
