Metadata-Version: 2.1
Name: py-fibonacci
Version: 0.5.2
Summary: Generates Fibonacci series with an end number OR a length argument.
Home-page: https://github.com/pydatageek/py-fibonacci
Author: Haluk Aksu
Author-email: pydatageek@gmail.com
License: UNKNOWN
Platform: UNKNOWN
Classifier: Programming Language :: Python :: 3
Classifier: License :: OSI Approved :: MIT License
Classifier: Operating System :: OS Independent
Classifier: Intended Audience :: Developers
Classifier: Topic :: Software Development :: Libraries
Requires-Python: >=3.6
